aiopogo/__init__.py
aiopogo/auth.py
aiopogo/auth_google.py
aiopogo/auth_ptc.py
aiopogo/connector.py
aiopogo/exceptions.py
aiopogo/hash_server.py
aiopogo/pgoapi.py
aiopogo/rpc_api.py
aiopogo/session.py
aiopogo/utilities.py
aiopogo/pogoprotos/__init__.py
aiopogo/pogoprotos/data/__init__.py
aiopogo/pogoprotos/data/asset_digest_entry_pb2.py
aiopogo/pogoprotos/data/background_token_pb2.py
aiopogo/pogoprotos/data/buddy_pokemon_pb2.py
aiopogo/pogoprotos/data/client_version_pb2.py
aiopogo/pogoprotos/data/download_url_entry_pb2.py
aiopogo/pogoprotos/data/food_value_pb2.py
aiopogo/pogoprotos/data/player_badge_pb2.py
aiopogo/pogoprotos/data/player_data_pb2.py
aiopogo/pogoprotos/data/pokedex_entry_pb2.py
aiopogo/pogoprotos/data/pokemon_data_pb2.py
aiopogo/pogoprotos/data/pokemon_display_pb2.py
aiopogo/pogoprotos/data/redeem_passcode_reward_pb2.py
aiopogo/pogoprotos/data/avatar/__init__.py
aiopogo/pogoprotos/data/avatar/avatar_customization_pb2.py
aiopogo/pogoprotos/data/avatar/avatar_item_pb2.py
aiopogo/pogoprotos/data/badge/__init__.py
aiopogo/pogoprotos/data/badge/awarded_gym_badge_pb2.py
aiopogo/pogoprotos/data/badge/badge_capture_reward_pb2.py
aiopogo/pogoprotos/data/badge/gym_badge_stats_pb2.py
aiopogo/pogoprotos/data/battle/__init__.py
aiopogo/pogoprotos/data/battle/battle_action_pb2.py
aiopogo/pogoprotos/data/battle/battle_action_type_pb2.py
aiopogo/pogoprotos/data/battle/battle_log_pb2.py
aiopogo/pogoprotos/data/battle/battle_participant_pb2.py
aiopogo/pogoprotos/data/battle/battle_pb2.py
aiopogo/pogoprotos/data/battle/battle_pokemon_info_pb2.py
aiopogo/pogoprotos/data/battle/battle_results_pb2.py
aiopogo/pogoprotos/data/battle/battle_state_pb2.py
aiopogo/pogoprotos/data/battle/battle_type_pb2.py
aiopogo/pogoprotos/data/battle/battle_update_pb2.py
aiopogo/pogoprotos/data/capture/__init__.py
aiopogo/pogoprotos/data/capture/capture_award_pb2.py
aiopogo/pogoprotos/data/capture/capture_probability_pb2.py
aiopogo-2.0.4.dist-info/DESCRIPTION.rst
aiopogo-2.0.4.dist-info/METADATA
aiopogo-2.0.4.dist-info/RECORD
aiopogo-2.0.4.dist-info/WHEEL
aiopogo-2.0.4.dist-info/metadata.json
aiopogo-2.0.4.dist-info/top_level.txt
